napari_biopb/__init__.py
napari_biopb/_grpc.py
napari_biopb/_typing.py
napari_biopb/_version.py
napari_biopb/_widget.py
napari_biopb/napari.yaml
napari_biopb/_tests/__init__.py
napari_biopb/_tests/test_widget.py
napari_biopb-0.1.4.dist-info/LICENSE
napari_biopb-0.1.4.dist-info/METADATA
napari_biopb-0.1.4.dist-info/WHEEL
napari_biopb-0.1.4.dist-info/entry_points.txt
napari_biopb-0.1.4.dist-info/top_level.txt
napari_biopb-0.1.4.dist-info/RECORD
