Metadata-Version: 2.2
Name: napari-biopb
Version: 0.1.4
Summary: Performing image analysis by visiting biopb endpoints
Author: Ji Yu
Author-email: jyu@uchc.edu
License: 
Project-URL: Bug Tracker, https://github.com/jiyuuchc/napari-biopb/issues
Project-URL: Documentation, https://github.com/jiyuuchc/napari-biopb#README.md
Project-URL: Source Code, https://github.com/jiyuuchc/napari-biopb
Project-URL: User Support, https://github.com/jiyuuchc/napari-biopb/issues
Classifier: Development Status :: 2 - Pre-Alpha
Classifier: Framework :: napari
Classifier: Intended Audience :: Developers
Classifier: License :: OSI Approved :: MIT License
Classifier: Operating System :: OS Independent
Classifier: Programming Language :: Python
Classifier: Programming Language :: Python :: 3
Classifier: Programming Language :: Python :: 3 :: Only
Classifier: Programming Language :: Python :: 3.9
Classifier: Programming Language :: Python :: 3.10
Classifier: Programming Language :: Python :: 3.11
Classifier: Programming Language :: Python :: 3.12
Classifier: Topic :: Scientific/Engineering :: Image Processing
Requires-Python: >=3.9
License-File: LICENSE
Requires-Dist: numpy
Requires-Dist: magicgui
Requires-Dist: qtpy
Requires-Dist: scikit-image
Requires-Dist: biopb
Requires-Dist: opencv-python-headless
Requires-Dist: grpcio_tools
Requires-Dist: vedo
Provides-Extra: testing
Requires-Dist: tox; extra == "testing"
Requires-Dist: pytest; extra == "testing"
Requires-Dist: pytest-cov; extra == "testing"
Requires-Dist: pytest-qt; extra == "testing"
Requires-Dist: napari; extra == "testing"
Requires-Dist: pyqt5; extra == "testing"
